spacy_stanza/__init__.py
spacy_stanza/about.py
spacy_stanza/tokenizer.py
spacy_stanza-1.0.4.dist-info/LICENSE
spacy_stanza-1.0.4.dist-info/METADATA
spacy_stanza-1.0.4.dist-info/WHEEL
spacy_stanza-1.0.4.dist-info/entry_points.txt
spacy_stanza-1.0.4.dist-info/top_level.txt
spacy_stanza-1.0.4.dist-info/RECORD
