Metadata-Version: 2.1
Name: spacy-stanza
Version: 1.0.4
Summary: Use the latest Stanza (StanfordNLP) research models directly in spaCy
Home-page: https://explosion.ai
Author: Explosion
Author-email: contact@explosion.ai
License: MIT
Project-URL: Release notes, https://github.com/explosion/spacy-stanza/releases
Project-URL: Source, https://github.com/explosion/spacy-stanza
Classifier: Development Status :: 4 - Beta
Classifier: Intended Audience :: Developers
Classifier: Topic :: Scientific/Engineering :: Artificial Intelligence
Classifier: Programming Language :: Python :: 3.6
Classifier: Programming Language :: Python :: 3.7
Classifier: Programming Language :: Python :: 3.8
Classifier: Programming Language :: Python :: 3.9
Classifier: Programming Language :: Python :: 3.10
Classifier: Programming Language :: Python :: 3.11
Requires-Python: >=3.6
License-File: LICENSE
Requires-Dist: spacy <4.0.0,>=3.0.0
Requires-Dist: stanza <1.7.0,>=1.2.0
